nanoserv.cpython-37m-x86_64-linux-gnu.so
setup.py
nanoserv-1.0.3.dist-info/METADATA
nanoserv-1.0.3.dist-info/WHEEL
nanoserv-1.0.3.dist-info/top_level.txt
nanoserv-1.0.3.dist-info/RECORD
