Metadata-Version: 2.1
Name: nanoserv
Version: 1.0.3
Summary: nanoserv.functorflow.org
Home-page: http://nanoserv.functorflow.org
Author: Sam Ravshanov
Author-email: info@functorflow.org
License: MIT
Project-URL: Home, https://nanoserv.functorflow.org/
Project-URL: Blog, https://medium.com/functorflow
Project-URL: Source, https://bitbucket.org/functorflow/functorflow-pip
Platform: UNKNOWN
Classifier: Development Status :: 5 - Production/Stable
Classifier: Intended Audience :: Developers
Classifier: Natural Language :: English
Classifier: License :: OSI Approved :: MIT License
Classifier: Programming Language :: Python
Classifier: Programming Language :: Python :: 3.4
Classifier: Programming Language :: Python :: 3.5
Classifier: Programming Language :: Python :: 3.6
Requires-Dist: gunicorn
Requires-Dist: Flask
